odoo10_addon_storage_thumbnail-10.0.1.0.1-py3.8-nspkg.pth
odoo/addons/storage_thumbnail/README.rst
odoo/addons/storage_thumbnail/__init__.py
odoo/addons/storage_thumbnail/__manifest__.py
odoo/addons/storage_thumbnail/data/ir_parameter.xml
odoo/addons/storage_thumbnail/i18n/storage_thumbnail.pot
odoo/addons/storage_thumbnail/models/__init__.py
odoo/addons/storage_thumbnail/models/storage_file.py
odoo/addons/storage_thumbnail/models/storage_thumbnail.py
odoo/addons/storage_thumbnail/models/thumbnail_mixin.py
odoo/addons/storage_thumbnail/security/ir.model.access.csv
odoo/addons/storage_thumbnail/static/description/icon.png
odoo/addons/storage_thumbnail/views/storage_thumbnail_view.xml
odoo10_addon_storage_thumbnail-10.0.1.0.1.dist-info/METADATA
odoo10_addon_storage_thumbnail-10.0.1.0.1.dist-info/WHEEL
odoo10_addon_storage_thumbnail-10.0.1.0.1.dist-info/namespace_packages.txt
odoo10_addon_storage_thumbnail-10.0.1.0.1.dist-info/top_level.txt
odoo10_addon_storage_thumbnail-10.0.1.0.1.dist-info/RECORD
